{
    "date": "2021-03-03 20:38:33.308418",
    "debug": {
        "baseline": 2.3522664382439844,
        "coding_deg": 28.877667315338314,
        "rf_pred": 2.3284184179250844,
        "temporal_deg": 0.0,
        "upscaling_deg": 32.48044415458403
    },
    "per_second": [
        2.312012315012811,
        2.2535274299649255,
        2.2192738268496948,
        2.3770247513494054,
        2.430715538874518,
        2.393528560916815,
        2.399137685945451
    ],
    "per_sequence": 2.3403424280845346,
    "video_basename": "american_football_harmonic_8s_1659kbps_360p_59.94fps_hevc.mp4",
    "video_full_path": "/media/data01/AVT-VQDB-UHD-1/segments/american_football_harmonic_8s_1659kbps_360p_59.94fps_hevc.mp4"
}